textfab/__init__.py
textfab/augmentations.py
textfab/base.py
textfab/emoji_tokenizer.py
textfab/fabric.py
textfab/units.py
textfab/utils.py
textfab-1.0.0.dist-info/LICENSE.md
textfab-1.0.0.dist-info/METADATA
textfab-1.0.0.dist-info/WHEEL
textfab-1.0.0.dist-info/top_level.txt
textfab-1.0.0.dist-info/RECORD
