Metadata-Version: 2.1
Name: textfab
Version: 1.0.0
Summary: A tiny library for text preprocessing in NLP
Home-page: https://github.com/Astromis/textfab
Author: Igor Buyanov
Author-email: buyanov.igor.o@yandex.ru
Project-URL: Bug Tracker, https://github.com/Astromis/textfab/issues
Classifier: Programming Language :: Python :: 3
Classifier: Operating System :: OS Independent
Requires-Python: >=3.6
License-File: LICENSE.md
Requires-Dist: pymystem3 >=0.2.0
Requires-Dist: nltk >=3.6.7
Requires-Dist: omegaconf >=2.3.0
